Metadata-Version: 2.1
Name: ccpy
Version: 0.0.5
Summary: Python Free Currency Converter
Home-page: https://github.com/chyi341152/ccpy
Author: Chyi's
Author-email: chyiyaqing@gmail.com
License: UNKNOWN
Project-URL: Bug Reports, https://github.com/chyi341152/ccpy/issues
Project-URL: Source, https://github.com/chyi341152/ccpy/
Keywords: Currency Converter Python
Platform: UNKNOWN
Classifier: Development Status :: 3 - Alpha
Classifier: Intended Audience :: Developers
Classifier: Topic :: Software Development :: Build Tools
Classifier: License :: OSI Approved :: MIT License
Classifier: Programming Language :: Python :: 3
Classifier: Programming Language :: Python :: 3.4
Classifier: Programming Language :: Python :: 3.5
Classifier: Programming Language :: Python :: 3.6
Provides-Extra: test
Provides-Extra: dev
